nonebot_plugin_tuan_chatgpt/__init__.py
nonebot_plugin_tuan_chatgpt/config.py
nonebot_plugin_tuan_chatgpt/perf_timer.py
nonebot_plugin_tuan_chatgpt/text_to_img.py
nonebot_plugin_tuan_chatgpt/utils.py
nonebot_plugin_tuan_chatgpt-0.4.2.dist-info/LICENSE.md
nonebot_plugin_tuan_chatgpt-0.4.2.dist-info/METADATA
nonebot_plugin_tuan_chatgpt-0.4.2.dist-info/WHEEL
nonebot_plugin_tuan_chatgpt-0.4.2.dist-info/RECORD
