Metadata-Version: 2.1
Name: nonebot_plugin_tuan_chatgpt
Version: 0.4.2
Summary: "Chat with tuanzi ~"
Home-page: https://github.com/TheLZY/nonebot_plugin_tuan_chatgpt
License: MIT
Author: TheLZY
Requires-Python: >=3.8,<4.0
Classifier: License :: OSI Approved :: MIT License
Classifier: Programming Language :: Python :: 3
Classifier: Programming Language :: Python :: 3.8
Classifier: Programming Language :: Python :: 3.9
Classifier: Programming Language :: Python :: 3.10
Classifier: Programming Language :: Python :: 3.11
Requires-Dist: Pillow (>=9.5.0,<10.0.0)
Requires-Dist: aiohttp (>=3.8.4,<4.0.0)
Requires-Dist: nonebot-adapter-onebot (>=2.2.0,<3.0.0)
Requires-Dist: nonebot2 (>=2.0.0rc3,<3.0.0)
Requires-Dist: openai (>=0.27.0,<0.28.0)
Requires-Dist: qrcode (>=7.4.2,<8.0.0)
Requires-Dist: tiktoken (>=0.3.0,<0.4.0)
Requires-Dist: urllib3 (==1.25.11)
Project-URL: Repository, https://github.com/TheLZY/nonebot_plugin_tuan_chatgpt
